mallows_models/__init__.py
mallows_models/mallows_hamming.py
mallows_models/mallows_kendall.py
mallows_models/mallows_model.py
mallows_models/permutil.py
mallows_models-0.1.0.dist-info/LICENSE
mallows_models-0.1.0.dist-info/METADATA
mallows_models-0.1.0.dist-info/WHEEL
mallows_models-0.1.0.dist-info/top_level.txt
mallows_models-0.1.0.dist-info/RECORD
